apache_beam/error.py
apache_beam/pipeline.py
apache_beam/version.py
apache_beam/__init__.py
apache_beam/pvalue.py
apache_beam/pvalue_test.py
apache_beam/py.typed
apache_beam/pipeline_test.py
apache_beam/yaml/pipeline.schema.yaml
apache_beam/yaml/yaml_transform_test.py
apache_beam/yaml/cache_provider_artifacts.py
apache_beam/yaml/yaml_provider_unit_test.py
apache_beam/yaml/yaml_combine_test.py
apache_beam/yaml/__init__.py
apache_beam/yaml/yaml_mapping.py
apache_beam/yaml/yaml_transform.py
apache_beam/yaml/yaml_io.py
apache_beam/yaml/readme_test.py
apache_beam/yaml/json_utils.py
apache_beam/yaml/yaml_io_test.py
apache_beam/yaml/yaml_provider.py
apache_beam/yaml/yaml_transform_scope_test.py
apache_beam/yaml/yaml_mapping_test.py
apache_beam/yaml/yaml_udf_test.py
apache_beam/yaml/yaml_combine.py
apache_beam/yaml/generate_yaml_docs.py
apache_beam/yaml/yaml_transform_unit_test.py
apache_beam/yaml/standard_io.yaml
apache_beam/yaml/options.py
apache_beam/yaml/standard_providers.yaml
apache_beam/yaml/main.py
apache_beam/io/tfrecordio_test.py
apache_beam/io/mongodbio_it_test.py
apache_beam/io/requestresponse_test.py
apache_beam/io/filesystems_test.py
apache_beam/io/iobase.py
apache_beam/io/requestresponse_it_test.py
apache_beam/io/mongodbio.py
apache_beam/io/avroio_test.py
apache_beam/io/kinesis.py
apache_beam/io/fileio_test.py
apache_beam/io/tfrecordio.py
apache_beam/io/range_trackers_test.py
apache_beam/io/utils_test.py
apache_beam/io/source_test_utils_test.py
apache_beam/io/__init__.py
apache_beam/io/filesystem.py
apache_beam/io/localfilesystem.py
apache_beam/io/snowflake.py
apache_beam/io/filesystemio.py
apache_beam/io/filebasedsink.py
apache_beam/io/hadoopfilesystem_test.py
apache_beam/io/concat_source.py
apache_beam/io/watermark_estimators_test.py
apache_beam/io/filesystemio_test.py
apache_beam/io/sources_test.py
apache_beam/io/source_test_utils.py
apache_beam/io/mongodbio_test.py
gli_apache_beam-2.54.1.dist-info/RECORD
gli_apache_beam-2.54.1.dist-info/top_level.txt
gli_apache_beam-2.54.1.dist-info/WHEEL
gli_apache_beam-2.54.1.dist-info/METADATA
