Metadata-Version: 2.1
Name: gli-apache-beam
Version: 2.54.1
Summary: Apache Beam SDK for Python
Home-page: https://beam.apache.org
Download-URL: https://pypi.python.org/pypi/apache-beam
Author: Apache Software Foundation
Author-email: dev@beam.apache.org
License: Apache License, Version 2.0
Keywords: apache beam
Classifier: Intended Audience :: End Users/Desktop
Classifier: License :: OSI Approved :: Apache Software License
Classifier: Operating System :: POSIX :: Linux
Classifier: Programming Language :: Python :: 3.8
Classifier: Programming Language :: Python :: 3.9
Classifier: Programming Language :: Python :: 3.10
Classifier: Programming Language :: Python :: 3.11
Classifier: Topic :: Software Development :: Libraries
Classifier: Topic :: Software Development :: Libraries :: Python Modules
Requires-Python: >=3.8
Provides-Extra: docs
Provides-Extra: test
Provides-Extra: gcp
Provides-Extra: interactive
Provides-Extra: interactive_test
Provides-Extra: aws
Provides-Extra: azure
Provides-Extra: dataframe
Provides-Extra: dask
Provides-Extra: yaml
